linesplan/__init__.py
linesplan/dxfreader.py
linesplan/lines.py
linesplan-0.1.1.dist-info/METADATA
linesplan-0.1.1.dist-info/WHEEL
linesplan-0.1.1.dist-info/RECORD
